web/__init__.py
web/application.py
web/browser.py
web/db.py
web/debugerror.py
web/form.py
web/http.py
web/httpserver.py
web/net.py
web/py3helpers.py
web/session.py
web/template.py
web/test.py
web/utils.py
web/webapi.py
web/wsgi.py
web/contrib/__init__.py
web/contrib/template.py
web/wsgiserver/__init__.py
web/wsgiserver/ssl_builtin.py
web/wsgiserver/ssl_pyopenssl.py
web/wsgiserver/wsgiserver2.py
web/wsgiserver/wsgiserver3.py
mywebpy-0.63.dist-info/LICENSE.txt
mywebpy-0.63.dist-info/METADATA
mywebpy-0.63.dist-info/WHEEL
mywebpy-0.63.dist-info/top_level.txt
mywebpy-0.63.dist-info/RECORD
