Metadata-Version: 2.1
Name: mywebpy
Version: 0.63
Summary: web.py: makes web apps
Home-page: http://webpy.org/
Author: Aaron Swartz
Author-email: me@aaronsw.com
Maintainer: Anand Chitipothu
Maintainer-email: anandology@gmail.com
License: Public domain
Platform: any
Classifier: License :: Public Domain
Classifier: Programming Language :: Python
Classifier: Programming Language :: Python :: 3
Classifier: Programming Language :: Python :: 3.5
Classifier: Programming Language :: Python :: 3.6
Classifier: Programming Language :: Python :: 3.7
Classifier: Programming Language :: Python :: 3.8
Classifier: Programming Language :: Python :: 3.9
Requires-Python: >=3.5
License-File: LICENSE.txt
